fifo.v
module fifo( clk,reset,d_in,wr_en,rd_en,full,empty,d_out,fifo_counter);

parameter DATA_WIDTH=8;
parameter DEPTH=16;

input clk,reset,wr_en,rd_en;
input [DATA_WIDTH-1:0]d_in;
output full,empty;
output [DATA_WIDTH-1:0]d_out;
output [4:0]fifo_counter;

wire clk;
wire reset;
wire [DATA_WIDTH-1:0]d_in;
wire wr_en;
wire rd_en;

reg full;
reg empty;
reg [DATA_WIDTH-1:0]d_out;
reg [4:0] fifo_counter;

//creating a reg called memory 
reg [DATA_WIDTH-1:0] memory [DEPTH-1:0];
reg [3:0] rd_ptr,wr_ptr;

//full and empty indication
always@(fifo_counter) begin
	empty=(fifo_counter==0);
	full=(fifo_counter==16);
end

//counter manipulation
always@(posedge clk or posedge reset) begin
	if(reset)
		fifo_counter<=0;
	else if((rd_en&&!empty) && (wr_en&&!full)) 
		fifo_counter<=fifo_counter;
	else if(wr_en&&!full)
		fifo_counter<=fifo_counter+1;
	else if(rd_en&&!empty)
		fifo_counter<=fifo_counter-1;
	else 
		fifo_counter<=fifo_counter;
end


//writing part

always@(posedge clk ) begin
	 if(wr_en&&!full) 
		memory[wr_ptr]<=d_in;
	else
		memory[wr_ptr]<=memory[wr_ptr];			  
end


//reading part 

always@(posedge clk or posedge reset) begin
	if(reset)
		d_out<=0;
	else if(rd_en && !empty)
		d_out<=memory[rd_ptr];
	else 
		d_out<=memory[rd_ptr];

end

// read write pointer manipulation

always@(posedge clk or posedge reset) begin
	if(reset) begin
		wr_ptr<=0;
		rd_ptr<=0;	
	end
	
	else if(wr_en&&!full)
		wr_ptr<=wr_ptr+1;
	else if(rd_en && !empty)
		rd_ptr<=rd_ptr+1;
	else begin
		rd_ptr<=rd_ptr;
		wr_ptr<=wr_ptr;
	     end
	     
end


endmodule

fifo_tb.v
module fifo_tb();
reg clk;
reg reset;
reg [7:0] d_in;
reg rd_en;
reg wr_en;

wire [7:0] d_out;
wire [4:0]fifo_counter;
wire full;
wire empty;

fifo dut(.clk(clk),.reset(reset),.d_in(d_in),.rd_en(rd_en),.wr_en(wr_en),.d_out(d_out),.fifo_counter(fifo_counter),.full(full),.empty(empty));

initial 
begin
$dumpfile("fifo_test.vcd");
$dumpvars(0,fifo_tb);
end

always #5 clk=~clk;

initial
begin
clk=1'b0;
reset=1'b1;
d_in=8'b10110001;
rd_en<=1'b0;
wr_en<=1'b1;

#20
reset=1'b0;
d_in=8'b10110001;
rd_en<=1'b0;
wr_en<=1'b1;

#20
reset=1'b0;
d_in=8'b10110001;
rd_en<=1'b1;
wr_en<=1'b0;

#20
reset=1'b0;
d_in=8'b11111101;
rd_en<=1'b0;
wr_en<=1'b1;

#20
reset=1'b0;
d_in=8'b10110001;
rd_en<=1'b1;
wr_en<=1'b0;

#500 $finish;

end
endmodule

fifo_test.vcd
$date
	Tue Apr 16 13:56:21 2024
$end
$version
	Icarus Verilog
$end
$timescale
	1s
$end
$scope module fifo_tb $end
$var wire 1 ! full $end
$var wire 5 " fifo_counter [4:0] $end
$var wire 1 # empty $end
$var wire 8 $ d_out [7:0] $end
$var reg 1 % clk $end
$var reg 8 & d_in [7:0] $end
$var reg 1 ' rd_en $end
$var reg 1 ( reset $end
$var reg 1 ) wr_en $end
$scope module dut $end
$var wire 1 % clk $end
$var wire 8 * d_in [7:0] $end
$var wire 1 ' rd_en $end
$var wire 1 ( reset $end
$var wire 1 ) wr_en $end
$var reg 8 + d_out [7:0] $end
$var reg 1 # empty $end
$var reg 5 , fifo_counter [4:0] $end
$var reg 1 ! full $end
$var reg 4 - rd_ptr [3:0] $end
$var reg 4 . wr_ptr [3:0] $end
$upscope $end
$upscope $end
$enddefinitions $end
#0
$dumpvars
b0 .
b0 -
b0 ,
b0 +
b10110001 *
1)
1(
0'
b10110001 &
0%
b0 $
1#
b0 "
0!
$end
#5
1%
#10
0%
#15
1%
#20
0%
0(
#25
0#
b1 .
b10110001 $
b10110001 +
b1 "
b1 ,
1%
#30
0%
#35
b10 "
b10 ,
b10 .
1%
#40
0)
1'
0%
#45
b1 -
b1 "
b1 ,
1%
#50
0%
#55
1#
b0 "
b0 ,
b10 -
1%
#60
1)
0'
0%
b11111101 &
b11111101 *
#65
0#
b11 .
bx $
bx +
b1 "
b1 ,
1%
#70
0%
#75
b10 "
b10 ,
b11111101 $
b11111101 +
b100 .
1%
#80
0)
1'
0%
b10110001 &
b10110001 *
#85
b11 -
b1 "
b1 ,
1%
#90
0%
#95
1#
b0 "
b0 ,
b100 -
1%
#100
0%
#105
bx $
bx +
1%
